Metadata-Version: 2.1
Name: odoo-addon-l10n_ro_fiscal_validation
Version: 19.0.0.1.0
Requires-Dist: odoo-addon-l10n_ro_partner_create_by_vat==19.0.*
Requires-Dist: odoo-addon-l10n_ro_vat_on_payment==19.0.*
Requires-Dist: odoo==19.0.*
Summary: Romania - Fiscal Validation
Home-page: https://github.com/OCA/l10n-romania
License: AGPL-3
Author: NextERP Romania,Forest and Biomass Romania,Odoo Community Association (OCA)
Author-email: support@odoo-community.org
Classifier: Programming Language :: Python
Classifier: Framework :: Odoo
Classifier: Framework :: Odoo :: 19.0
Classifier: License :: OSI Approved :: GNU Affero General Public License v3
Classifier: Development Status :: 6 - Mature
